napari_hierarchical/__init__.py
napari_hierarchical/_controller.py
napari_hierarchical/_reader.py
napari_hierarchical/_version.py
napari_hierarchical/hookspecs.py
napari_hierarchical/model.py
napari_hierarchical/napari.yaml
napari_hierarchical/_tests/__init__.py
napari_hierarchical/_tests/test_dummy.py
napari_hierarchical/contrib/__init__.py
napari_hierarchical/contrib/hdf5/__init__.py
napari_hierarchical/contrib/hdf5/_reader.py
napari_hierarchical/contrib/hdf5/_writer.py
napari_hierarchical/contrib/hdf5/model.py
napari_hierarchical/contrib/imc/__init__.py
napari_hierarchical/contrib/imc/_reader.py
napari_hierarchical/contrib/imc/model.py
napari_hierarchical/contrib/zarr/__init__.py
napari_hierarchical/contrib/zarr/_reader.py
napari_hierarchical/contrib/zarr/_writer.py
napari_hierarchical/contrib/zarr/model.py
napari_hierarchical/sample_data/__init__.py
napari_hierarchical/sample_data/idr0052A.py
napari_hierarchical/sample_data/imc_mock.py
napari_hierarchical/sample_data/pollen.py
napari_hierarchical/utils/__init__.py
napari_hierarchical/utils/parent_aware.py
napari_hierarchical/utils/proxy_image.py
napari_hierarchical/widgets/__init__.py
napari_hierarchical/widgets/_arrays_widget.py
napari_hierarchical/widgets/_flat_grouping_tree_model.py
napari_hierarchical/widgets/_flat_grouping_tree_view.py
napari_hierarchical/widgets/_flat_groupings_tab_widget.py
napari_hierarchical/widgets/_group_tree_model.py
napari_hierarchical/widgets/_group_tree_view.py
napari_hierarchical/widgets/_groups_widget.py
napari_hierarchical/widgets/resources/__init__.py
napari_hierarchical/widgets/resources/resources.py
napari_hierarchical/widgets/resources/resources.qrc
napari_hierarchical/widgets/resources/icons/loaded.svg
napari_hierarchical/widgets/resources/icons/loaded_off.svg
napari_hierarchical/widgets/resources/icons/loaded_partial.svg
napari_hierarchical/widgets/resources/icons/visible.svg
napari_hierarchical/widgets/resources/icons/visible_off.svg
napari_hierarchical-0.1.0.dist-info/LICENSE
napari_hierarchical-0.1.0.dist-info/METADATA
napari_hierarchical-0.1.0.dist-info/WHEEL
napari_hierarchical-0.1.0.dist-info/entry_points.txt
napari_hierarchical-0.1.0.dist-info/top_level.txt
napari_hierarchical-0.1.0.dist-info/RECORD
