Metadata-Version: 2.1
Name: napari-hierarchical
Version: 0.1.0
Summary: Hierarchical file format support for napari
Home-page: https://github.com/BodenmillerGroup/napari-hierarchical
Author: Jonas Windhager
Author-email: jonas.windhager@uzh.ch
License: MIT
Project-URL: Bug Tracker, https://github.com/BodenmillerGroup/napari-hierarchical/issues
Project-URL: Documentation, https://github.com/BodenmillerGroup/napari-hierarchical#README.md
Project-URL: Source Code, https://github.com/BodenmillerGroup/napari-hierarchical
Project-URL: User Support, https://github.com/BodenmillerGroup/napari-hierarchical/issues
Classifier: Framework :: napari
Classifier: License :: OSI Approved :: MIT License
Classifier: Operating System :: OS Independent
Classifier: Programming Language :: Python
Classifier: Programming Language :: Python :: 3
Classifier: Programming Language :: Python :: 3 :: Only
Classifier: Programming Language :: Python :: 3.8
Classifier: Programming Language :: Python :: 3.9
Classifier: Programming Language :: Python :: 3.10
Classifier: Topic :: Scientific/Engineering :: Image Processing
Requires-Python: <3.11,>=3.8
License-File: LICENSE
Requires-Dist: napari (<0.4.18,>=0.4.17)
Requires-Dist: pluggy
Requires-Dist: qtpy
Provides-Extra: all
Requires-Dist: dask ; extra == 'all'
Requires-Dist: h5py ; extra == 'all'
Requires-Dist: readimc ; extra == 'all'
Requires-Dist: s3fs ; extra == 'all'
Requires-Dist: zarr ; extra == 'all'
Provides-Extra: hdf5
Requires-Dist: dask ; extra == 'hdf5'
Requires-Dist: h5py ; extra == 'hdf5'
Provides-Extra: imc
Requires-Dist: dask ; extra == 'imc'
Requires-Dist: readimc ; extra == 'imc'
Provides-Extra: testing
Requires-Dist: tox ; extra == 'testing'
Requires-Dist: pytest ; extra == 'testing'
Requires-Dist: pytest-cov ; extra == 'testing'
Requires-Dist: pytest-qt ; extra == 'testing'
Requires-Dist: napari ; extra == 'testing'
Requires-Dist: pyqt5 ; extra == 'testing'
Provides-Extra: zarr
Requires-Dist: dask ; extra == 'zarr'
Requires-Dist: s3fs ; extra == 'zarr'
Requires-Dist: zarr ; extra == 'zarr'
